nonebot_plugin_scheduled_broadcast-0.1.5.dist-info/METADATA
nonebot_plugin_scheduled_broadcast-0.1.5.dist-info/WHEEL
nonebot_plugin_scheduled_broadcast-0.1.5.dist-info/licenses/LICENSE
nonebot_plugin_scheduled_broadcast/__init__.py
nonebot_plugin_scheduled_broadcast/config.py
nonebot_plugin_scheduled_broadcast/core.py
nonebot_plugin_scheduled_broadcast/db.py
nonebot_plugin_scheduled_broadcast-0.1.5.dist-info/RECORD
