Metadata-Version: 2.1
Name: nonebot-plugin-scheduled-broadcast
Version: 0.1.5
Summary: A customizable, adapter-independent, event-based scheduled broadcaster aiming for all nonebot2 adapters.
Keywords: nonebot2 scheduler broadcast
Author-Email: Tony Xiang <tonyxfy@qq.com>
License: MIT
Requires-Python: >=3.8
Requires-Dist: nonebot2>=2.0.0
Requires-Dist: nonebot-plugin-apscheduler<1.0.0,>=0.3.0
